neighgen/__init__.py
neighgen/__main__.py
neighgen/core.py
neighgen/ngen.py
neighgen/settings.py
neighgen/version.py
neighgen/extras/example.dk-config.yaml
neighgen/extras/example.env
neighgen/extras/example.yaml
neighgen/templates/neigh_ios.j2
neighgen/templates/neigh_nxos.j2
privex_neighgen-0.8.0.data/scripts/neighgen
privex_neighgen-0.8.0.dist-info/LICENSE
privex_neighgen-0.8.0.dist-info/LICENSE.txt
privex_neighgen-0.8.0.dist-info/METADATA
privex_neighgen-0.8.0.dist-info/WHEEL
privex_neighgen-0.8.0.dist-info/top_level.txt
privex_neighgen-0.8.0.dist-info/RECORD
