Metadata-Version: 2.1
Name: privex-neighgen
Version: 0.8.0
Summary: NeighGen - A BGP neighbour config generator written in Python, using PeeringDB's API to discover ASN BGP addresses
Home-page: https://github.com/Privex/neighgen
Author: Chris (Someguy123) @ Privex
Author-email: chris@privex.io
License: MIT
Platform: UNKNOWN
Classifier: Programming Language :: Python :: 3
Classifier: Programming Language :: Python :: 3.7
Classifier: Programming Language :: Python :: 3.8
Classifier: Programming Language :: Python :: 3.9
Classifier: Programming Language :: Python :: 3.10
Classifier: License :: OSI Approved :: MIT License
Classifier: Operating System :: OS Independent
License-File: LICENSE
License-File: LICENSE.txt
Requires-Dist: privex-helpers[setuppy] (>=3.0)
Requires-Dist: privex-loghelper
Requires-Dist: privex-db
Requires-Dist: peeringdb (>=1.2.1)
Requires-Dist: Django
Requires-Dist: django-peeringdb (>=2.9)
Requires-Dist: psycopg2
Requires-Dist: PyYAML
Requires-Dist: jinja2
Requires-Dist: rich
Requires-Dist: dicttoxml
Requires-Dist: python-dotenv
